afbfdb/Protocol.py
afbfdb/__init__.py
pyafbfdb-0.1.4.dist-info/licenses/AUTHORS.rst
pyafbfdb-0.1.4.dist-info/licenses/LICENSE.rst
pyafbfdb-0.1.4.dist-info/METADATA
pyafbfdb-0.1.4.dist-info/WHEEL
pyafbfdb-0.1.4.dist-info/entry_points.txt
pyafbfdb-0.1.4.dist-info/top_level.txt
pyafbfdb-0.1.4.dist-info/RECORD
