Metadata-Version: 2.4
Name: PyAFBFdb
Version: 0.1.4
Summary: Generation of texture database from the package PyAFBF
Home-page: https://github.com/fjprichard/PyAFBFdb/
Author: Frédéric Richard
Author-email: frederic.richard@univ-amu.fr
License: GPLv3
Project-URL: Documentation, https://fjprichard.github.io/PyAFBFdb/
Project-URL: Source, https://github.com/fjprichard/PyAFBFdb/
Project-URL: Tracker, https://github.com/fjprichard/PyAFBFdb/issues
Keywords: image texture,simulation,database,anisotropic fractional Brownian field
Platform: Linux
Platform: MacOSX
Platform: Windows
Classifier: License :: OSI Approved :: GNU General Public License v3 (GPLv3)
Classifier: Development Status :: 3 - Alpha
Classifier: Intended Audience :: Science/Research
Classifier: Intended Audience :: End Users/Desktop
Classifier: Intended Audience :: Developers
Classifier: Natural Language :: English
Classifier: Operating System :: OS Independent
Classifier: Programming Language :: Python :: 3.8
Classifier: Topic :: Scientific/Engineering :: Image Processing
License-File: LICENSE.rst
License-File: AUTHORS.rst
Requires-Dist: PyAFBF>=0.2.3
Requires-Dist: matplotlib>=3.3.2
Requires-Dist: scipy>=1.5.2
Requires-Dist: imageio>=2.9.0
Dynamic: author
Dynamic: author-email
Dynamic: classifier
Dynamic: description
Dynamic: home-page
Dynamic: keywords
Dynamic: license
Dynamic: license-file
Dynamic: platform
Dynamic: project-url
Dynamic: requires-dist
Dynamic: summary
